zzfdemo/__init__.py
zzfdemo/common.py
zzfdemo/foliumap.py
zzfdemo/utils.py
zzfdemo/zzfdemo.py
zzfdemo-0.0.5.dist-info/LICENSE
zzfdemo-0.0.5.dist-info/METADATA
zzfdemo-0.0.5.dist-info/WHEEL
zzfdemo-0.0.5.dist-info/dependency_links.txt
zzfdemo-0.0.5.dist-info/top_level.txt
zzfdemo-0.0.5.dist-info/RECORD
