Metadata-Version: 2.1
Name: zzfdemo
Version: 0.0.5
Summary: zzf demo
Home-page: https://github.com/ITzzF/zzfdemo
Author: Zhifan Zhang
Author-email: 2692219488@qq.com
License: MIT license
Keywords: zzfdemo
Classifier: Intended Audience :: Developers
Classifier: License :: OSI Approved :: MIT License
Classifier: Natural Language :: English
Classifier: Programming Language :: Python :: 3
Classifier: Programming Language :: Python :: 3.8
Classifier: Programming Language :: Python :: 3.9
Classifier: Programming Language :: Python :: 3.10
Classifier: Programming Language :: Python :: 3.11
Requires-Python: >=3.8
License-File: LICENSE
Requires-Dist: numpy
Requires-Dist: ipyleaflet
Requires-Dist: pandas
Requires-Dist: localtileserver
Requires-Dist: folium
